LICENSE
README.md
setup.py
stooqer/__init__.py
stooqer/stooqer.py
stooqer.egg-info/PKG-INFO
stooqer.egg-info/SOURCES.txt
stooqer.egg-info/dependency_links.txt
stooqer.egg-info/requires.txt
stooqer.egg-info/top_level.txt