Metadata-Version: 2.1
Name: stooqer
Version: 1.0.0
Summary: Stooq data download into pandas DataFrame
Author: Septixu (Michał Lachowicz)
Author-email: <michal.lachowicz@protnmail.com>
Keywords: python,stock,stooq,finance
Classifier: Development Status :: 1 - Planning
Classifier: Intended Audience :: Developers
Classifier: Programming Language :: Python :: 3
Classifier: Operating System :: Unix
Classifier: Operating System :: MacOS :: MacOS X
Classifier: Operating System :: Microsoft :: Windows
License-File: LICENSE
